LICENSE
MANIFEST.in
README.md
pyproject.toml
setup.py
src/_kepler.c
src/_kepler.pyx
src/kepler.c
src/fast_kepler.egg-info/PKG-INFO
src/fast_kepler.egg-info/SOURCES.txt
src/fast_kepler.egg-info/dependency_links.txt
src/fast_kepler.egg-info/top_level.txt