Metadata-Version: 2.1
Name: fast_kepler
Version: 0.5.1
Summary: kepler equation solver in c for python
Author: ReddTea
License: MIT
Classifier: Programming Language :: Python :: 3
Classifier: Programming Language :: Cython
Classifier: License :: OSI Approved :: MIT License
Classifier: Operating System :: OS Independent
Requires-Python: >=3.6
License-File: LICENSE
